captacity/__init__.py
captacity/cli.py
captacity/segment_parser.py
captacity/text_drawer.py
captacity/transcriber.py
captacity/assets/fonts/Bangers-Regular-LICENSE.txt
captacity/assets/fonts/Bangers-Regular.ttf
captacity/assets/fonts/Knewave-Regular-LICENSE.txt
captacity/assets/fonts/Knewave-Regular.ttf
captacity/assets/fonts/PoetsenOne-Regular-LICENSE.txt
captacity/assets/fonts/PoetsenOne-Regular.ttf
captacity-0.3.1.dist-info/LICENSE
captacity-0.3.1.dist-info/METADATA
captacity-0.3.1.dist-info/WHEEL
captacity-0.3.1.dist-info/entry_points.txt
captacity-0.3.1.dist-info/top_level.txt
captacity-0.3.1.dist-info/RECORD
