Metadata-Version: 2.1
Name: captacity
Version: 0.3.1
Summary: Add Automatic Captions to YouTube Shorts with AI
Home-page: https://github.com/unconv/captacity
Author: Unconventional Coding
Author-email: unconventionalcoding@gmail.com
License: MIT
License-File: LICENSE
Requires-Dist: moviepy
Requires-Dist: pillow
Requires-Dist: openai
Provides-Extra: local_whisper
Requires-Dist: openai-whisper ; extra == 'local_whisper'
